kaipy/__init__.py
kaipy/cdaweb_utils.py
kaipy/embiggenUtils.py
kaipy/kJobs.py
kaipy/kaiH5.py
kaipy/kaiTools.py
kaipy/kaiViz.py
kaipy/kaijson.py
kaipy/kaixdmf.py
kaipy/kdefs.py
kaipy/supermage.py
kaipy/transform.py
kaipy/chimp/__init__.py
kaipy/chimp/chimph5p.py
kaipy/chimp/chimpviz.py
kaipy/chimp/kCyl.py
kaipy/cmaps/__init__.py
kaipy/cmaps/cmDDiv.txt
kaipy/cmaps/cmMLT.txt
kaipy/cmaps/kaimaps.py
kaipy/gamera/__init__.py
kaipy/gamera/deltabViz.py
kaipy/gamera/gamGrids.py
kaipy/gamera/gampp.py
kaipy/gamera/lfmG.X.txt
kaipy/gamera/lfmG.Y.txt
kaipy/gamera/magsphere.py
kaipy/gamera/magsphereRescale.py
kaipy/gamera/msphViz.py
kaipy/gamera/rcmpp.py
kaipy/gamera/remixpp.py
kaipy/gamhelio/__init__.py
kaipy/gamhelio/helioViz.py
kaipy/gamhelio/heliosphere.py
kaipy/gamhelio/lib/__init__.py
kaipy/gamhelio/lib/wsa.py
kaipy/gamhelio/wsa2gamera/__init__.py
kaipy/gamhelio/wsa2gamera/params.py
kaipy/paraview/__init__.py
kaipy/paraview/pvGam.py
kaipy/paraview/pvutils.py
kaipy/raiju/__init__.py
kaipy/raiju/dst.py
kaipy/raiju/m2m.py
kaipy/raiju/raijuUtils.py
kaipy/raiju/raijuViz.py
kaipy/raiju/lambdautils/AlamData.py
kaipy/raiju/lambdautils/AlamParams.py
kaipy/raiju/lambdautils/DistTypes.py
kaipy/raiju/lambdautils/__init__.py
kaipy/raiju/lambdautils/fileIO.py
kaipy/raiju/waveModel/__init__.py
kaipy/raiju/waveModel/chorus_polynomial.txt
kaipy/raiju/waveModel/genWM.py
kaipy/raiju/waveModel/wmData.py
kaipy/rcm/__init__.py
kaipy/rcm/dktable
kaipy/rcm/enchan.dat
kaipy/rcm/rcminit.py
kaipy/rcm/rcmutils.py
kaipy/rcm/rcmxdmf.py
kaipy/rcm/lambdautils/AlamData.py
kaipy/rcm/lambdautils/AlamParams.py
kaipy/rcm/lambdautils/DistTypes.py
kaipy/rcm/lambdautils/__init__.py
kaipy/rcm/lambdautils/fileIO.py
kaipy/rcm/lambdautils/genAlam.py
kaipy/rcm/lambdautils/plotter.py
kaipy/rcm/wmutils/__init__.py
kaipy/rcm/wmutils/chorus_polynomial.txt
kaipy/rcm/wmutils/genWM.py
kaipy/rcm/wmutils/wmData.py
kaipy/remix/__init__.py
kaipy/remix/remix.py
kaipy/satcomp/__init__.py
kaipy/satcomp/scRCM.py
kaipy-1.1.3.dist-info/licenses/LICENSE.md
kaipy-1.1.3.dist-info/METADATA
kaipy-1.1.3.dist-info/WHEEL
kaipy-1.1.3.dist-info/entry_points.txt
kaipy-1.1.3.dist-info/top_level.txt
kaipy-1.1.3.dist-info/RECORD
