Metadata-Version: 2.4
Name: kaipy
Version: 1.1.3
Summary: Python software for CGS MAGE and other Kaiju models
Home-page: https://bitbucket.org/aplkaiju/kaipy/src/master/
Author: Kaiju team
Author-email: Eric Winter <eric.winter@jhuapl.edu>
License: BSD 3-Clause
Keywords: CGS,MAGE,KAIJU
Classifier: Programming Language :: Python :: 3
Requires-Python: >=3.9,<3.13
License-File: LICENSE.md
Requires-Dist: alive_progress
Requires-Dist: astropy
Requires-Dist: cartopy
Requires-Dist: cdasws
Requires-Dist: cmasher
Requires-Dist: configparser
Requires-Dist: h5py
Requires-Dist: jupyterlab
Requires-Dist: matplotlib
Requires-Dist: pandas
Requires-Dist: progressbar
Requires-Dist: pyspedas
Requires-Dist: pytest
Requires-Dist: slack_sdk
Requires-Dist: spacepy
Requires-Dist: sphinx-rtd-theme
Requires-Dist: sphinxcontrib-autoprogram
Requires-Dist: sunpy
Requires-Dist: gfz-api-client
Requires-Dist: supermag-api
Dynamic: author
Dynamic: home-page
Dynamic: license-file
Dynamic: requires-python
